owner/__init__.py
owner/base.py
owner/util.py
owner-0.0.10.dist-info/LICENSE
owner-0.0.10.dist-info/METADATA
owner-0.0.10.dist-info/WHEEL
owner-0.0.10.dist-info/top_level.txt
owner-0.0.10.dist-info/RECORD
