Metadata-Version: 2.1
Name: owner
Version: 0.0.10
Summary: Tools to prove ownership of content
Home-page: https://github.com/thorwhalen/owner
Author: Thor Whalen
License: mit
Platform: any
